aiobittrex/__init__.py
aiobittrex/api.py
aiobittrex/errors.py
aiobittrex/socket.py
aiobittrex/tests/__init__.py
aiobittrex/tests/test_replace_keys.py
aiobittrex-0.2.0.dist-info/METADATA
aiobittrex-0.2.0.dist-info/RECORD
aiobittrex-0.2.0.dist-info/WHEEL
aiobittrex-0.2.0.dist-info/top_level.txt
