Metadata-Version: 2.1
Name: aiobittrex
Version: 0.2.0
Summary: Async Bittrex api wrapper.
Home-page: https://github.com/nanvel/aiobittrex
Author: Oleksandr Polieno
Author-email: polyenoom@gmail.com
License: The MIT License
Keywords: async,bittrex
Platform: OS Independent
Requires-Dist: aiohttp (==3.5.4)
Requires-Dist: asyncio-throttle (==0.1.1)
